{
    "Company": "BLACKSANDINVEST",
    "Logo": "https://design.ejobs.ro/assets/img/colorPositiveOrange.07ea350f.png",
    "Jobs": [
        {
            "company": "BLACKSANDINVEST",
            "job_title": "Expert cadastru si carte funciara specialist Eterra",
            "job_link": "https://www.ejobs.ro/user/locuri-de-munca/expert-cadastru-si-carte-funciara-specialist-eterra/1692732",
            "job_logo": "No logo found",
            "job_location": "Bucuresti",
            "country": "Romania"
        },
        {
            "id": "6a423649-f9cc-496e-8b83-0947dad7b172",
            "company": "BLACKSANDINVEST",
            "job_title": "Expert cadastru si carte funciara specialist Eterra",
            "job_link": "https://www.ejobs.ro/user/locuri-de-munca/expert-cadastru-si-carte-funciara-specialist-eterra/1692732",
            "job_logo": "https://design.ejobs.ro/assets/img/colorPositiveOrange.07ea350f.png",
            "job_location": "Bucuresti",
            "country": "Romania"
        },
        {
            "id": "acc6deba-2e75-4ade-a2da-269e9095f26d",
            "company": "BLACKSANDINVEST",
            "job_title": "Expert cadastru si carte funciara specialist Eterra",
            "job_link": "https://www.ejobs.ro/user/locuri-de-munca/expert-cadastru-si-carte-funciara-specialist-eterra/1692732",
            "job_logo": "https://design.ejobs.ro/assets/img/colorPositiveOrange.07ea350f.png",
            "city": "Bucuresti",
            "country": "Romania"
        },
        {
            "id": "6b64e2f1-7b93-40c0-a1ce-8572c4ddd750",
            "company": "BLACKSANDINVEST",
            "job_title": "Expert cadastru si carte funciara specialist Eterra",
            "job_link": "https://www.ejobs.ro/user/locuri-de-munca/expert-cadastru-si-carte-funciara-specialist-eterra/1692732",
            "job_logo": "https://design.ejobs.ro/assets/img/colorPositiveOrange.07ea350f.png",
            "city": "Bucuresti",
            "country": "Romania"
        },
        {
            "id": "3bcd0464-0af7-46d3-91ee-a8e805ce234f",
            "company": "BLACKSANDINVEST",
            "job_title": "Expert cadastru si carte funciara specialist Eterra",
            "job_link": "https://www.ejobs.ro/user/locuri-de-munca/expert-cadastru-si-carte-funciara-specialist-eterra/1692732",
            "job_logo": "https://design.ejobs.ro/assets/img/colorPositiveOrange.07ea350f.png",
            "city": "Bucuresti",
            "country": "Romania"
        },
        {
            "id": "cf28bfcb-2ba2-4872-b599-a6e7f23137cf",
            "company": "BLACKSANDINVEST",
            "job_title": "Expert cadastru si carte funciara specialist Eterra",
            "job_link": "https://www.ejobs.ro/user/locuri-de-munca/expert-cadastru-si-carte-funciara-specialist-eterra/1692732",
            "job_logo": "https://design.ejobs.ro/assets/img/colorPositiveOrange.07ea350f.png",
            "city": "Bucuresti",
            "country": "Romania"
        }
    ]
}